gf/__init__.py
gf/dialog.py
gf/emoji.py
gf/feature.py
gf/hotfix.py
gf/inspector.py
gf/main.py
gf/test.py
gf/utils.py
gitflo-0.0.2.dist-info/LICENSE
gitflo-0.0.2.dist-info/METADATA
gitflo-0.0.2.dist-info/WHEEL
gitflo-0.0.2.dist-info/entry_points.txt
gitflo-0.0.2.dist-info/top_level.txt
gitflo-0.0.2.dist-info/RECORD
