Metadata-Version: 2.1
Name: gitflo
Version: 0.0.2
Summary: git-flow branch management with standard commit format
Home-page: https://github.com/Be5yond/gf
Author: Be5yond
Author-email: beyond147896@126.com
License: UNKNOWN
Platform: UNKNOWN
Classifier: Programming Language :: Python :: 3
Classifier: License :: OSI Approved :: Apache Software License
Classifier: Operating System :: OS Independent
Requires-Python: >=3.6
Requires-Dist: gitpython
Requires-Dist: typer
Requires-Dist: prompt-toolkit
